app/__init__.py
app/main.py
app/logic/__init__.py
app/logic/background_calculator.py
app/logic/enhanced_data_loader.py
app/logic/fast_image_loader.py
app/logic/file_io.py
app/logic/frontend_cache_manager.py
app/logic/geometry_calculator.py
app/logic/image_renderer.py
app/logic/secondary_renderers.py
app/logic/streamlined_image_manager.py
app/logic/synchronous_vtk_renderer.py
app/logic/threaded_processes.py
app/logic/ui_state_manager.py
app/logic/threads/__init__.py
app/logic/threads/background_threads.py
app/logic/threads/base_worker.py
app/logic/threads/geometry_utils.py
app/logic/threads/image_processing_threads.py
app/logic/threads/loss_utils.py
app/logic/threads/model_threads.py
app/logic/threads/qdrant_threads.py
app/logic/threads/streamlined_loading_thread.py
app/logic/threads/threshold_update_thread.py
app/logic/threads/utility_threads.py
app/logic/threads/vtk_computation_utils.py
app/ui/__init__.py
app/ui/csv_export_utils.py
app/ui/embedded_features.ui
app/ui/embedded_features_window.py
app/ui/geometric_features.ui
app/ui/geometric_features_window.py
app/ui/mainWindow.ui
app/ui/main_window.py
app/ui/model_summary.py
app/ui/preferences.py
app/ui/preferences.ui
app/ui/progress_dialog.py
app/ui/statistical_threshold_dialog.py
app/ui/status_lamp.py
app/ui/threshold_dialog.py
app/ui/ui_data_mixin.py
app/ui/ui_handlers_mixin.py
app/ui/ui_processing_mixin.py
app/ui/ui_rendering_mixin.py
app/ui/ui_setup_mixin.py
app/ui/ui_utils_mixin.py
app/utils/__init__.py
app/utils/benchmark.py
app/utils/cli_loader.py
app/utils/debug_config.py
app/utils/imports.py
app/utils/logging_config.py
app/utils/resource_loader.py
neutrophils_classifier-1.0.1.dist-info/licenses/LICENSE
neutrophils_classifier-1.0.1.dist-info/METADATA
neutrophils_classifier-1.0.1.dist-info/WHEEL
neutrophils_classifier-1.0.1.dist-info/entry_points.txt
neutrophils_classifier-1.0.1.dist-info/top_level.txt
neutrophils_classifier-1.0.1.dist-info/RECORD
