Metadata-Version: 2.4
Name: neutrophils-classifier
Version: 1.0.1
Summary: A GUI application for neutrophil classification using deep learning models
Author-email: Jacky Ka Long Ko <ka.ko@kennedy.ox.ac.uk>
License: MIT
Project-URL: Homepage, https://github.com/bpi-oxford/Neutrophils-Classifier-App
Project-URL: Repository, https://github.com/bpi-oxford/Neutrophils-Classifier-App
Project-URL: Issues, https://github.com/bpi-oxford/Neutrophils-Classifier-App/issues
Classifier: Development Status :: 4 - Beta
Classifier: Intended Audience :: Science/Research
Classifier: License :: OSI Approved :: MIT License
Classifier: Operating System :: OS Independent
Classifier: Programming Language :: Python :: 3
Classifier: Programming Language :: Python :: 3.9
Classifier: Programming Language :: Python :: 3.10
Classifier: Programming Language :: Python :: 3.11
Classifier: Topic :: Scientific/Engineering :: Artificial Intelligence
Classifier: Topic :: Scientific/Engineering :: Image Processing
Requires-Python: >=3.9
License-File: LICENSE
Requires-Dist: neutrophils-core>=0.1.0
Requires-Dist: PyQt5>=5.15.0
Requires-Dist: numpy>=1.21.0
Requires-Dist: pandas>=1.3.0
Requires-Dist: scikit-learn>=1.0.0
Requires-Dist: matplotlib>=3.5.0
Requires-Dist: seaborn>=0.11.0
Requires-Dist: vtk>=9.0.0
Requires-Dist: qdrant-client>=1.0.0
Requires-Dist: Pillow>=8.3.0
Requires-Dist: tqdm>=4.62.0
Dynamic: license-file
